StockPrices
