Metadata-Version: 2.1
Name: LiveStockPrice
Version: 2
Summary: A webscrapper to get live price of any stock
Home-page: https://github.com/TheA12W/LiveStockPrice
Author: adrianw
Author-email: 
License: MIT
Platform: UNKNOWN
License-File: LICENSE.txt
